{
    "Monday": {
        "1000": [
            "1D",
            "1E",
            "1F",
            "3B",
            "3C",
            "3D",
            "3E",
            "3F",
            "3G",
            "4A"
        ],
        "1020": [
            "1D",
            "1E",
            "1F",
            "3B",
            "3C",
            "3D",
            "3E",
            "3F",
            "3G",
            "4A"
        ],
        "1040": [
            "1A",
            "1B",
            "1C",
            "2D",
            "4D"
        ],
        "1060": [
            "1A",
            "1B",
            "1C",
            "2D",
            "4D"
        ],
        "1100": [
            "2A",
            "2B",
            "2C",
            "3A",
            "4E",
            "4F"
        ],
        "1120": [
            "1G",
            "2A",
            "2B",
            "2C",
            "3A",
            "4E",
            "4F"
        ],
        "1140": [
            "1G"
        ],
        "0940": [
            "2E",
            "2F"
        ],
        "0960": [
            "2E",
            "2F"
        ],
        "0900": [
            "4B",
            "4C",
            "4G",
            "4H"
        ],
        "0920": [
            "4B",
            "4C",
            "4G",
            "4H"
        ]
    },
    "Tuesday": {
        "1000": [
            "1G",
            "2D",
            "2E",
            "2F",
            "3B",
            "3C"
        ],
        "1020": [
            "1G",
            "2D",
            "2E",
            "2F",
            "3B",
            "3C",
            "4H"
        ],
        "1040": [
            "2A",
            "3D",
            "4D",
            "4G",
            "4H"
        ],
        "1060": [
            "2A",
            "3D",
            "4D",
            "4G"
        ],
        "1100": [
            "1D",
            "1E",
            "1F"
        ],
        "1120": [
            "1D",
            "1E",
            "1F",
            "4C"
        ],
        "1140": [
            "4C"
        ],
        "0920": [
            "1A",
            "1B",
            "1C",
            "3A",
            "3E",
            "3F",
            "3G",
            "4A",
            "4E",
            "4F"
        ],
        "0940": [
            "1A",
            "1B",
            "1C",
            "2B",
            "2C",
            "4B"
        ],
        "0960": [
            "2B",
            "2C",
            "4B"
        ],
        "0900": [
            "3A",
            "3E",
            "3F",
            "3G",
            "4A",
            "4E",
            "4F"
        ]
    },
    "Wednesday": {
        "1020": [
            "1D",
            "1G",
            "2A",
            "2B",
            "3A"
        ],
        "1040": [
            "1D",
            "1G",
            "2A",
            "2B",
            "3A",
            "3D",
            "3E",
            "3F",
            "3G",
            "4B",
            "4H"
        ],
        "1060": [
            "3D",
            "3E",
            "3F",
            "3G",
            "4B",
            "4H"
        ],
        "1100": [
            "2C"
        ],
        "1120": [
            "1E",
            "1F",
            "2C",
            "3B",
            "3C",
            "4A",
            "4D",
            "4G"
        ],
        "1140": [
            "1E",
            "1F",
            "3B",
            "3C",
            "4A",
            "4D",
            "4G"
        ],
        "0940": [
            "1A",
            "1B",
            "1C",
            "2D",
            "2E",
            "2F",
            "4C",
            "4E",
            "4F"
        ],
        "0960": [
            "1A",
            "1B",
            "1C",
            "2D",
            "2E",
            "2F",
            "4C",
            "4E",
            "4F"
        ]
    },
    "Thursday": {
        "1020": [
            "2F",
            "3A"
        ],
        "1040": [
            "2F",
            "3A",
            "3C",
            "3D",
            "3G",
            "4A",
            "4B",
            "4C",
            "4D",
            "4E",
            "4F",
            "4G",
            "4H"
        ],
        "1060": [
            "3C",
            "3D",
            "3G",
            "4A",
            "4B",
            "4C",
            "4D",
            "4E",
            "4F",
            "4G",
            "4H"
        ],
        "1100": [
            "2D"
        ],
        "1120": [
            "2D",
            "2E"
        ],
        "1140": [
            "2E"
        ],
        "0940": [
            "1A",
            "1B",
            "1C",
            "1D",
            "1E",
            "1F",
            "1G",
            "2A",
            "2B",
            "2C",
            "3B",
            "3E",
            "3F"
        ],
        "0960": [
            "1A",
            "1B",
            "1C",
            "1D",
            "1E",
            "1F",
            "1G",
            "2A",
            "2B",
            "2C",
            "3B",
            "3E",
            "3F"
        ]
    },
    "Friday": {
        "1020": [
            "3B",
            "3E",
            "3F"
        ],
        "1040": [
            "1A",
            "1B",
            "1C",
            "2D",
            "2F",
            "3B",
            "3E",
            "3F",
            "4B",
            "4C",
            "4D",
            "4F",
            "4G"
        ],
        "1060": [
            "1A",
            "1B",
            "1C",
            "2D",
            "2F",
            "4B",
            "4C",
            "4D",
            "4F",
            "4G"
        ],
        "1100": [
            "3C",
            "3D",
            "3G"
        ],
        "1120": [
            "3C",
            "3D",
            "3G"
        ],
        "0940": [
            "1D",
            "1E",
            "1F",
            "1G",
            "2A",
            "2B",
            "2C",
            "2E",
            "3A",
            "4A",
            "4E",
            "4H"
        ],
        "0960": [
            "1D",
            "1E",
            "1F",
            "1G",
            "2A",
            "2B",
            "2C",
            "2E",
            "3A",
            "4A",
            "4E",
            "4H"
        ]
    }
}